[{"__symbolic":"module","version":3,"metadata":{"SafePipeModule":{"__symbolic":"class","decorators":[{"__symbolic":"call","expression":{"__symbolic":"reference","module":"@angular/core","name":"NgModule"},"arguments":[{"declarations":[{"__symbolic":"reference","module":"./safe.pipe","name":"SafePipe"}],"exports":[{"__symbolic":"reference","module":"./safe.pipe","name":"SafePipe"}],"imports":[{"__symbolic":"reference","module":"@angular/common","name":"CommonModule"}]}]}]}}},{"__symbolic":"module","version":1,"metadata":{"SafePipeModule":{"__symbolic":"class","decorators":[{"__symbolic":"call","expression":{"__symbolic":"reference","module":"@angular/core","name":"NgModule"},"arguments":[{"declarations":[{"__symbolic":"reference","module":"./safe.pipe","name":"SafePipe"}],"exports":[{"__symbolic":"reference","module":"./safe.pipe","name":"SafePipe"}],"imports":[{"__symbolic":"reference","module":"@angular/common","name":"CommonModule"}]}]}]}}}]